{
    "url": "/rest/projects/m6grbb1jnejh1bp1/md/dashboards/hram75ivsrsi6l61",
    "dumpTime": "2020-11-29T13:37:38Z",
    "version": "18",
    "content": {
        "id": "hram75ivsrsi6l61",
        "name": "rating_dashboard",
        "type": "dashboard",
        "content": {
            "blockRows": [
                {
                    "type": "indicator",
                    "indicator": "/rest/projects/$projectId/md/indicators?name=final_rating_indicator",
                    "indicatorDrill": "/rest/projects/$projectId/md/indicatorDrills?name=rating_final_indicator_drill",
                    "layout": "primary"
                },
                {
                    "type": "indicatorGroup",
                    "title": "Rating of Finance Metrics",
                    "collapsed": true,
                    "blockRows": [
                        {
                            "type": "blockRow",
                            "blocks": [
                                {
                                    "type": "indicator",
                                    "indicator": "/rest/projects/$projectId/md/indicators?name=rating_revenue_indicator",
                                    "indicatorDrill": "/rest/projects/$projectId/md/indicatorDrills?name=rating_indicator_drill",
                                    "layout": "primary"
                                },
                                {
                                    "type": "indicator",
                                    "indicator": "/rest/projects/$projectId/md/indicators?name=rating_profit_indicator",
                                    "indicatorDrill": "/rest/projects/$projectId/md/indicatorDrills?name=rating_indicator_drill",
                                    "layout": "primary"
                                }
                            ]
                        },
                        {
                            "type": "blockRow",
                            "blocks": [
                                {
                                    "type": "indicator",
                                    "indicator": "/rest/projects/$projectId/md/indicators?name=rating_gross_margin_indicator",
                                    "indicatorDrill": "/rest/projects/$projectId/md/indicatorDrills?name=rating_indicator_drill",
                                    "layout": "primary"
                                },
                                {
                                    "type": "indicator",
                                    "indicator": "/rest/projects/$projectId/md/indicators?name=rating_revenue_per_m_indicator",
                                    "indicatorDrill": "/rest/projects/$projectId/md/indicatorDrills?name=rating_indicator_drill",
                                    "layout": "primary"
                                }
                            ]
                        }
                    ],
                    "description": "Rating of financial metrics on range 0-100"
                },
                {
                    "type": "indicatorGroup",
                    "title": "Rating of Location Metrics",
                    "collapsed": true,
                    "blockRows": [
                        {
                            "type": "blockRow",
                            "blocks": [
                                {
                                    "type": "indicator",
                                    "indicator": "/rest/projects/$projectId/md/indicators?name=rating_exposure_indicator",
                                    "indicatorDrill": "/rest/projects/$projectId/md/indicatorDrills?name=rating_indicator_drill",
                                    "layout": "primary"
                                },
                                {
                                    "type": "indicator",
                                    "indicator": "/rest/projects/$projectId/md/indicators?name=rating_demography_indicator",
                                    "indicatorDrill": "/rest/projects/$projectId/md/indicatorDrills?name=rating_indicator_drill",
                                    "layout": "primary"
                                }
                            ]
                        }
                    ]
                }
            ]
        },
        "accessInfo": {
            "createdAt": "2020-11-22T15:09:54Z",
            "modifiedAt": "2020-11-28T21:45:00Z",
            "createdBy": "/rest/accounts/00uulrio7wrtJ9roK0h7",
            "modifiedBy": "/rest/accounts/00uulrio7wrtJ9roK0h7"
        },
        "links": [
            {
                "rel": "self",
                "href": "/rest/projects/m6grbb1jnejh1bp1/md/dashboards/hram75ivsrsi6l61"
            }
        ]
    }
}